kliamka.py
kliamka-0.4.0.dist-info/licenses/LICENSE
kliamka-0.4.0.dist-info/METADATA
kliamka-0.4.0.dist-info/WHEEL
kliamka-0.4.0.dist-info/top_level.txt
kliamka-0.4.0.dist-info/RECORD
